infi.datatable-0.5-py2.7-nspkg.pth
infi/datatable/__init__.py
infi/datatable/__version__.py
infi/datatable/static/datatable/infi.datatable.js
infi/datatable/static/datatable/infi.datatable.utils.js
infi.datatable-0.5.dist-info/METADATA
infi.datatable-0.5.dist-info/WHEEL
infi.datatable-0.5.dist-info/entry_points.txt
infi.datatable-0.5.dist-info/namespace_packages.txt
infi.datatable-0.5.dist-info/top_level.txt
infi.datatable-0.5.dist-info/RECORD
