Metadata-Version: 2.1
Name: infi.datatable
Version: 0.5
Summary: This project provides Backbone/Bootstrap components for displaying Infinidat-style collections
Home-page: https://git.infinidat.com/host-opensource/infi.datatable
Author: Itai Shirav
Author-email: itais@infinidat.com
License: BSD
Platform: UNKNOWN
Classifier: Intended Audience :: Developers
Classifier: Intended Audience :: System Administrators
Classifier: License :: OSI Approved :: BSD License
Classifier: Operating System :: OS Independent
Classifier: Programming Language :: Python
Classifier: Topic :: Software Development :: Libraries :: Python Modules
Requires-Dist: setuptools
